federated_collection_discovery/__init__.py
federated_collection_discovery/cmr_collection_search.py
federated_collection_discovery/collection_search.py
federated_collection_discovery/config.py
federated_collection_discovery/free_text.py
federated_collection_discovery/hint.py
federated_collection_discovery/main.py
federated_collection_discovery/models.py
federated_collection_discovery/shared.py
federated_collection_discovery/stac_api_collection_search.py
federated_collection_discovery-0.1.9.dist-info/METADATA
federated_collection_discovery-0.1.9.dist-info/WHEEL
federated_collection_discovery-0.1.9.dist-info/top_level.txt
federated_collection_discovery-0.1.9.dist-info/RECORD
