Metadata-Version: 2.2
Name: federated-collection-discovery
Version: 0.1.9
Summary: An application for discovering collections from multiple STAC APIs and/or CMRs
Author-email: Henry Rodman <henry@developmentseed.org>
License: MIT
Project-URL: homepage, https://github.com/developmentseed/federated-collection-discovery
Requires-Python: >=3.10
Requires-Dist: pystac-client>=0.8.4
Requires-Dist: stac-fastapi-types>=3.0.0
Requires-Dist: pydantic-settings>=2.3.4
Requires-Dist: black>=24.4.2
Requires-Dist: httpx>=0.27.2
Requires-Dist: python-cmr>=0.11.0
Requires-Dist: fastapi>=0.111.1
Provides-Extra: aws-lambda
Requires-Dist: mangum>=0.17.0; extra == "aws-lambda"
Provides-Extra: uvicorn
Requires-Dist: uvicorn>=0.30.1; extra == "uvicorn"
